foxwire/__init__.py
foxwire/cli.py
foxwire/foxwire.py
foxwire-0.1.0.dist-info/licenses/LICENSE
tests/FXS50_FoxWire.py
tests/FXS50_change_addr.py
tests/FXS50_configure.py
tests/FoxWire.py
tests/FoxWire_scandump.py
tests/FoxWire_test.py
tests/tests.py
foxwire-0.1.0.dist-info/METADATA
foxwire-0.1.0.dist-info/WHEEL
foxwire-0.1.0.dist-info/entry_points.txt
foxwire-0.1.0.dist-info/top_level.txt
foxwire-0.1.0.dist-info/RECORD
