Metadata-Version: 2.4
Name: foxwire
Version: 0.1.0
Summary: Python implementation of the FoxWire protocol
Author-email: Luis Felipe <foxdynamics@gmail.com>
License-Expression: MIT
Project-URL: Homepage, https://github.com/luisf18/foxwire
Project-URL: Repository, https://github.com/luisf18/foxwire
Classifier: Programming Language :: Python :: 3
Classifier: Operating System :: OS Independent
Requires-Python: >=3.6
License-File: LICENSE
Dynamic: license-file
